lyzr/__init__.py
lyzr/base/__init__.py
lyzr/base/base.py
lyzr/base/errors.py
lyzr/base/llm.py
lyzr/base/llms.py
lyzr/base/logger.py
lyzr/base/prompt.py
lyzr/base/prompt_old.py
lyzr/base/prompt_texts.py
lyzr/base/retrievers.py
lyzr/base/service.py
lyzr/base/vector_store.py
lyzr/base/prompts/__init__.py
lyzr/base/prompts/ai_queries_context_pt.txt
lyzr/base/prompts/ai_queries_pt.txt
lyzr/base/prompts/analysis_guide_pt.txt
lyzr/base/prompts/analysis_recommendations_pt.txt
lyzr/base/prompts/analysis_steps_pt.txt
lyzr/base/prompts/dataset_description_context_pt.txt
lyzr/base/prompts/dataset_description_pt.txt
lyzr/base/prompts/format_user_input_pt.txt
lyzr/base/prompts/insights_context_pt.txt
lyzr/base/prompts/insights_pt.txt
lyzr/base/prompts/plotting_guide_pt.txt
lyzr/base/prompts/plotting_steps_pt.txt
lyzr/base/prompts/plotting_steps_with_analysis_pt.txt
lyzr/base/prompts/recommendations_pt.txt
lyzr/base/prompts/rectxt_closing_text_pt.txt
lyzr/base/prompts/rectxt_default_context_pt.txt
lyzr/base/prompts/rectxt_json_output_pt.txt
lyzr/base/prompts/rectxt_task_no_insights_pt.txt
lyzr/base/prompts/rectxt_task_with_insights_pt.txt
lyzr/base/prompts/rectxt_text_output_pt.txt
lyzr/base/prompts/sql_prompt_pt.txt
lyzr/base/prompts/sql_question_gen_pt.txt
lyzr/base/prompts/tasks_context_pt.txt
lyzr/base/prompts/tasks_pt.txt
lyzr/chat/__init__.py
lyzr/chat/chatbot.py
lyzr/data_analyzr/__init__.py
lyzr/data_analyzr/analyzr.py
lyzr/data_analyzr/db_connector.py
lyzr/data_analyzr/db_models.py
lyzr/data_analyzr/file_utils.py
lyzr/data_analyzr/models.py
lyzr/data_analyzr/utils.py
lyzr/data_analyzr/vector_store_utils.py
lyzr/data_analyzr/analysis_handler/__init__.py
lyzr/data_analyzr/analysis_handler/plotter.py
lyzr/data_analyzr/analysis_handler/pythonic.py
lyzr/data_analyzr/analysis_handler/sql.py
lyzr/data_analyzr/analysis_handler/utils.py
lyzr/formula_generator/__init__.py
lyzr/formula_generator/formula_generator.py
lyzr/generator/__init__.py
lyzr/generator/generator.py
lyzr-0.1.42.dist-info/LICENSE.txt
lyzr-0.1.42.dist-info/METADATA
lyzr-0.1.42.dist-info/WHEEL
lyzr-0.1.42.dist-info/top_level.txt
lyzr-0.1.42.dist-info/RECORD
