Metadata-Version: 2.1
Name: lyzr
Version: 0.1.42
Home-page: 
Author: lyzr
Classifier: Programming Language :: Python :: 3
Classifier: License :: OSI Approved :: MIT License
Classifier: Operating System :: OS Independent
Requires-Python: >=3.8.1, <3.12
License-File: LICENSE.txt
Requires-Dist: openai
Requires-Dist: litellm
Requires-Dist: asyncio
Requires-Dist: nest-asyncio
Requires-Dist: llama-index ==0.9.4
Requires-Dist: langchain ==0.0.339
Requires-Dist: python-dotenv >=1.0.0
Requires-Dist: beautifulsoup4 ==4.12.2
Requires-Dist: pandas ==2.0.2
Requires-Dist: weaviate-client ==3.25.3
Requires-Dist: llmsherpa
Provides-Extra: data-analyzr
Requires-Dist: aenum ; extra == 'data-analyzr'
Requires-Dist: matplotlib ==3.8.2 ; extra == 'data-analyzr'
Requires-Dist: seaborn ==0.13.2 ; extra == 'data-analyzr'
Requires-Dist: scikit-learn ==1.4.0 ; extra == 'data-analyzr'
Requires-Dist: statsmodels ==0.14.1 ; extra == 'data-analyzr'
Requires-Dist: chromadb ==0.4.22 ; extra == 'data-analyzr'
Requires-Dist: tabulate ==0.9.0 ; extra == 'data-analyzr'
Requires-Dist: pmdarima ==2.0.4 ; extra == 'data-analyzr'
Requires-Dist: openpyxl ==3.1.2 ; extra == 'data-analyzr'
Requires-Dist: redshift-connector ==2.0.918 ; extra == 'data-analyzr'
Requires-Dist: psycopg2-binary ==2.9.9 ; extra == 'data-analyzr'
